azure/__init__.py
azure/cli/__init__.py
azure/cli/command_modules/__init__.py
azure/cli/command_modules/monitor/__init__.py
azure/cli/command_modules/monitor/_autoscale_util.py
azure/cli/command_modules/monitor/_client_factory.py
azure/cli/command_modules/monitor/_exception_handler.py
azure/cli/command_modules/monitor/_help.py
azure/cli/command_modules/monitor/_params.py
azure/cli/command_modules/monitor/actions.py
azure/cli/command_modules/monitor/commands.py
azure/cli/command_modules/monitor/custom.py
azure/cli/command_modules/monitor/transformers.py
azure/cli/command_modules/monitor/util.py
azure/cli/command_modules/monitor/validators.py
azure/cli/command_modules/monitor/grammar/MetricAlertConditionLexer.py
azure/cli/command_modules/monitor/grammar/MetricAlertConditionListener.py
azure/cli/command_modules/monitor/grammar/MetricAlertConditionParser.py
azure/cli/command_modules/monitor/grammar/MetricAlertConditionValidator.py
azure/cli/command_modules/monitor/grammar/__init__.py
azure/cli/command_modules/monitor/operations/__init__.py
azure/cli/command_modules/monitor/operations/action_groups.py
azure/cli/command_modules/monitor/operations/activity_log_alerts.py
azure/cli/command_modules/monitor/operations/autoscale-parameters-template.json
azure/cli/command_modules/monitor/operations/autoscale_settings.py
azure/cli/command_modules/monitor/operations/diagnostics_settings.py
azure/cli/command_modules/monitor/operations/log_profiles.py
azure/cli/command_modules/monitor/operations/metric_alert.py
azure_cli_monitor-0.2.15.dist-info/METADATA
azure_cli_monitor-0.2.15.dist-info/WHEEL
azure_cli_monitor-0.2.15.dist-info/top_level.txt
azure_cli_monitor-0.2.15.dist-info/RECORD
